YODE_Segmentation/predict_molecular.py
YODE_Segmentation/Image_Processing/biggest_shadow.py
YODE_Segmentation/Image_Processing/binary_img.py
YODE_Segmentation/Image_Processing/get_threshold_keys.py
YODE_Segmentation/Image_Processing/resize_img.py
YODE_Segmentation/deeplab_v3/get_palette.py
YODE_Segmentation/deeplab_v3/my_dataset.py
YODE_Segmentation/deeplab_v3/predict.py
YODE_Segmentation/deeplab_v3/train.py
YODE_Segmentation/deeplab_v3/train_multi_GPU.py
YODE_Segmentation/deeplab_v3/transforms.py
YODE_Segmentation/deeplab_v3/validation.py
YODE_Segmentation/deeplab_v3/src/__init__.py
YODE_Segmentation/deeplab_v3/src/deeplabv3_model.py
YODE_Segmentation/deeplab_v3/src/mobilenet_backbone.py
YODE_Segmentation/deeplab_v3/src/resnet_backbone.py
YODE_Segmentation/deeplab_v3/train_utils/__init__.py
YODE_Segmentation/deeplab_v3/train_utils/distributed_utils.py
YODE_Segmentation/deeplab_v3/train_utils/train_and_eval.py
YODE_Segmentation/yolov5/detect.py
YODE_Segmentation/yolov5/export.py
YODE_Segmentation/yolov5/hubconf.py
YODE_Segmentation/yolov5/train.py
YODE_Segmentation/yolov5/val.py
YODE_Segmentation/yolov5/models/__init__.py
YODE_Segmentation/yolov5/models/common.py
YODE_Segmentation/yolov5/models/experimental.py
YODE_Segmentation/yolov5/models/tf.py
YODE_Segmentation/yolov5/models/yolo.py
YODE_Segmentation/yolov5/paper_data/clauculate_anchors.py
YODE_Segmentation/yolov5/paper_data/kmeans.py
YODE_Segmentation/yolov5/paper_data/split_train_val.py
YODE_Segmentation/yolov5/paper_data/voc_label.py
YODE_Segmentation/yolov5/utils/__init__.py
YODE_Segmentation/yolov5/utils/activations.py
YODE_Segmentation/yolov5/utils/augmentations.py
YODE_Segmentation/yolov5/utils/autoanchor.py
YODE_Segmentation/yolov5/utils/autobatch.py
YODE_Segmentation/yolov5/utils/benchmarks.py
YODE_Segmentation/yolov5/utils/callbacks.py
YODE_Segmentation/yolov5/utils/datasets.py
YODE_Segmentation/yolov5/utils/downloads.py
YODE_Segmentation/yolov5/utils/general.py
YODE_Segmentation/yolov5/utils/loss.py
YoDe_Segmentation_v2-1.0.1.dist-info/LICENSE
YoDe_Segmentation_v2-1.0.1.dist-info/METADATA
YoDe_Segmentation_v2-1.0.1.dist-info/WHEEL
YoDe_Segmentation_v2-1.0.1.dist-info/entry_points.txt
YoDe_Segmentation_v2-1.0.1.dist-info/top_level.txt
YoDe_Segmentation_v2-1.0.1.dist-info/RECORD
