Metadata-Version: 2.1
Name: YoDe_Segmentation_v2
Version: 1.0.1
Home-page: https://github.com/OneChorm/YoDe-Segmentation
Author: zconechorm
Author-email: Email:zconechorm@163.com
Classifier: Programming Language :: Python :: 3.7
Classifier: License :: OSI Approved :: MIT License
Classifier: Operating System :: OS Independent
License-File: LICENSE
